diavatly/__init__.py
diavatly/diavatly.py
diavatly-2.0.7.dist-info/LICENSE
diavatly-2.0.7.dist-info/METADATA
diavatly-2.0.7.dist-info/WHEEL
diavatly-2.0.7.dist-info/top_level.txt
diavatly-2.0.7.dist-info/RECORD
