Metadata-Version: 2.1
Name: diavatly
Version: 2.0.7
Summary: A geophysics toolbox package
Home-page: https://github.com/robinthibaut/diavatly
Author: Robin Thibaut
Author-email: Robin.Thibaut@UGent.be
License: UNKNOWN
Platform: UNKNOWN
Classifier: Programming Language :: Python :: 3
Classifier: License :: OSI Approved :: MIT License
Classifier: Operating System :: OS Independent
Requires-Python: >=3.6
Requires-Dist: numpy
Requires-Dist: matplotlib
